tno/mpc/encryption_schemes/shamir/__init__.py
tno/mpc/encryption_schemes/shamir/py.typed
tno/mpc/encryption_schemes/shamir/shamir.py
tno/mpc/encryption_schemes/shamir/shamir_secret_sharing_integers.py
tno/mpc/encryption_schemes/shamir/utils.py
tno/mpc/encryption_schemes/shamir/test/__init__.py
tno/mpc/encryption_schemes/shamir/test/test_shamir_secret_sharing.py
tno/mpc/encryption_schemes/shamir/test/test_shamir_secret_sharing_integers.py
tno.mpc.encryption_schemes.shamir-1.3.2.dist-info/LICENSE
tno.mpc.encryption_schemes.shamir-1.3.2.dist-info/METADATA
tno.mpc.encryption_schemes.shamir-1.3.2.dist-info/WHEEL
tno.mpc.encryption_schemes.shamir-1.3.2.dist-info/top_level.txt
tno.mpc.encryption_schemes.shamir-1.3.2.dist-info/RECORD
