Metadata-Version: 2.1
Name: tno.mpc.encryption_schemes.shamir
Version: 1.3.2
Summary: Implementation of Shamir secret sharing
Author-email: TNO PET Lab <petlab@tno.nl>
Maintainer-email: TNO PET Lab <petlab@tno.nl>
License: Apache License, Version 2.0
Project-URL: Homepage, https://pet.tno.nl/
Project-URL: Documentation, https://docs.pet.tno.nl/mpc/encryption_schemes/shamir/1.3.2
Project-URL: Source, https://github.com/TNO-MPC/encryption_schemes.shamir
Keywords: TNO,MPC,multi-party computation,encryption schemes,distributed,shamir,cryptosystem
Platform: any
Classifier: License :: OSI Approved :: Apache Software License
Classifier: Programming Language :: Python :: 3
Classifier: Operating System :: OS Independent
Classifier: Intended Audience :: Developers
Classifier: Intended Audience :: Information Technology
Classifier: Intended Audience :: Science/Research
Classifier: Typing :: Typed
Classifier: Topic :: Security :: Cryptography
Requires-Python: >=3.8
License-File: LICENSE
Requires-Dist: sympy
Requires-Dist: tno.mpc.encryption_schemes.utils>=0.8.0
Requires-Dist: tno.mpc.communication~=4.0
Provides-Extra: gmpy
Requires-Dist: tno.mpc.encryption_schemes.utils[gmpy]; extra == "gmpy"
Provides-Extra: tests
Requires-Dist: pytest>=8.1; extra == "tests"
Requires-Dist: pytest-asyncio; extra == "tests"
